Metadata-Version: 2.1
Name: numbering2pdf
Version: 1.0.1
Summary: Adds numbering to pdf file
Home-page: https://github.com/vlad-anisov/numbering2pdf
Author: Vlad Anisov
Author-email: anisoffgo@gmail.com
License: Apache 2.0
Platform: UNKNOWN
